wannier19/__berry.py
wannier19/__berry_old.py
wannier19/__data_dk.py
wannier19/__dos.py
wannier19/__evaluate.py
wannier19/__gyrotropic.py
wannier19/__init__.py
wannier19/__integrate.py
wannier19/__kpoint.py
wannier19/__main.py
wannier19/__nonabelian.py
wannier19/__result.py
wannier19/__spin.py
wannier19/__symmetry.py
wannier19/__system.py
wannier19/__tabulate.py
wannier19/__utility.py
wannier19/__version.py
wannier19-0.1.2.dist-info/LICENSE
wannier19-0.1.2.dist-info/METADATA
wannier19-0.1.2.dist-info/WHEEL
wannier19-0.1.2.dist-info/top_level.txt
wannier19-0.1.2.dist-info/RECORD
