Metadata-Version: 2.1
Name: wannier19
Version: 0.1.2
Summary: Advanced tool for Wannier interpolation
Home-page: https://github.com/stepan-tsirkin/wannier19
Author: Stepan S. Tsirkin
Author-email: stepan.tsirkin@uzh.ch
License: UNKNOWN
Platform: UNKNOWN
Classifier: Programming Language :: Python :: 3
Classifier: License :: OSI Approved :: GNU General Public License v2 (GPLv2)
Classifier: Operating System :: OS Independent
Requires-Dist: colorama
Requires-Dist: lazy-property
Requires-Dist: numpy
Requires-Dist: pyfiglet
Requires-Dist: scipy (>=1.0)
Requires-Dist: termcolor
